{
    "page": {
        "key": "credit",
        "title": "Кредиты",
        "iconUrl": "https://assets.finuslugi.ru/mp-assets/images/mapp/icons/credit.png",
        "activeIconUrl": "https://assets.finuslugi.ru/mp-assets/images/mapp/icons/credit-active.png",
        "analytics": {
            "eventCategory": "credit_mob",
            "eventAction": "main_page_view"
        },
        "layout": [
            {
                "component": "creditProductCard",
                "key": "creditProductCard",
                "props": {
                    "displayType": "cardSingle"
                },
                "prefetched": true
            },
            {
                "component": "creditProductCard",
                "key": "survey",
                "props": {
                    "displayType": "cardSingle",
                    "title": "Опрос"
                },
                "prefetched": true
            },
            {
                "component": "offers",
                "key": "offers.creditOffers",
                "props": {
                    "context": "creditOffers",
                    "title": "Предложения",
                    "displayType": "specialOffer",
                    "displayCount": 1
                },
                "prefetched": true
            },
            {
                "component": "usefulTopics",
                "key": "usefulTopics.organizations",
                "prefetched": true,
                "props": {
                    "context": "organizations",
                    "displayType": "cardSimple",
                    "title": "Полезное",
                    "description": "Посмотреть организации своего города, отсортировать, найти по названию"
                }
            }
        ]
    },
    "data": [
        {
            "title": "Кредит на любые цели",
            "description": "Не выходя из дома",
            "background": {
                "url": "https://dev-minio.beta.moex.com/mp-assets/images/credit/banner1.png"
            },
            "actionText": "Получить кредит",
            "deepLink": "finuslugi://credits",
            "custom": {
                "state": "no-credit"
            },
            "analytics": {
                "eventCategory": "credit_mob",
                "eventAction": "banner_click",
                "eventLabel": "uncover"
            },
            "layoutKey": "creditProductCard"
        },
        {
            "title": "Помогите нам стать лучше",
            "description": "Ответьте на 1 вопрос",
            "actionText": "Пройти опрос",
            "actionUrl": "https://ru.surveymonkey.com/r/FZBHQYD",
            "custom": {
                "state": "no-credit"
            },
            "layoutKey": "survey"
        },
        {
            "title": "Стань агентом и зарабатывай с Финуслугами",
            "background": {
                "url": "https://dev-minio.beta.moex.com/mp-assets/images/credit/offer1.png",
                "colors": [
                    "#D7BFFF"
                ]
            },
            "actionUrl": "https://agents.finuslugi.ru",
            "analytics": {
                "eventCategory": "credit_mob",
                "eventAction": "agent_click"
            },
            "layoutKey": "offers.creditOffers"
        },
        {
            "actionUrl": "https://finuslugi.ru/banki",
            "analytics": {
                "eventAction": "topic_click",
                "eventCategory": "credits_mob",
                "eventLabel": "banks"
            },
            "background": {
                "url": "https://dev-minio.beta.moex.com/mp-assets/images/credit/useful1.png",
                "colors": [
                    "#EAEBEE"
                ]
            },
            "layoutKey": "usefulTopics.organizations",
            "title": "Банки"
        },
        {
            "actionUrl": "https://finuslugi.ru/strahovanie_kompanija",
            "analytics": {
                "eventAction": "topic_click",
                "eventCategory": "credits_mob",
                "eventLabel": "insurance"
            },
            "background": {
                "url": "https://dev-minio.beta.moex.com/mp-assets/images/credit/useful2.png",
                "colors": [
                    "#EAEBEE"
                ]
            },
            "layoutKey": "usefulTopics.organizations",
            "title": "Страховые"
        },
        {
            "actionUrl": "https://finuslugi.ru/navigator/kredity",
            "analytics": {
                "eventAction": "topic_click",
                "eventCategory": "credits_mob",
                "eventLabel": "insurance"
            },
            "background": {
                "url": "https://dev-minio.beta.moex.com/mp-assets/images/credit/useful3.png",
                "colors": [
                    "#EAEBEE"
                ]
            },
            "layoutKey": "usefulTopics.organizations",
            "title": "Статьи про кредиты",
            "description": "Полезный контент от экспертов рынка"
        }
    ]
}
